cdr_fuentex/__init__.py
cdr_fuentex/cdr_fuentex.py
cdr_fuentex-0.1.1.dist-info/LICENSE
cdr_fuentex-0.1.1.dist-info/METADATA
cdr_fuentex-0.1.1.dist-info/WHEEL
cdr_fuentex-0.1.1.dist-info/top_level.txt
cdr_fuentex-0.1.1.dist-info/RECORD
