Metadata-Version: 2.2
Name: cdr_fuentex
Version: 0.1.1
Summary: Librería para calcular el Coeficiente de Dispersión Relativa Fuentex (CDR-FX).
Home-page: https://github.com/FuentexDatalab/cdr_fuentex
Author: FuentexDatalab
Author-email: fuentex.datalab@gmail.com
Classifier: Programming Language :: Python :: 3
Classifier: License :: OSI Approved :: MIT License
Classifier: Operating System :: OS Independent
Requires-Python: >=3.7
License-File: LICENSE
Requires-Dist: pandas
Dynamic: author
Dynamic: author-email
Dynamic: classifier
Dynamic: description
Dynamic: description-content-type
Dynamic: home-page
Dynamic: requires-dist
Dynamic: requires-python
Dynamic: summary
